{"stat.drop.minecraft.stone_pickaxe":1,"stat.craftItem.mw.leadingot":3,"stat.pickup.minecraft.wooden_slab":1,"stat.horseOneCm":60196,"stat.leaveGame":25,"stat.mineBlock.minecraft.cobblestone":56,"stat.pickup.minecraft.stone_pickaxe":1,"stat.pickup.minecraft.flint":1,"stat.mineBlock.minecraft.brown_mushroom":6,"stat.mineBlock.ic2.rubber_wood":1,"stat.pickup.forestry.resources":43,"stat.pickup.mw.sulfurdust":14,"stat.swimOneCm":7913,"stat.useItem.minecraft.planks":686,"stat.climbOneCm":4468,"stat.pickup.mw.aug":1,"stat.mineBlock.mw.sulfurore":17,"stat.pickup.mw.bauxiteore":3,"stat.pickup.minecraft.porkchop":7,"stat.pickup.ic2.hazmat_leggings":1,"stat.useItem.minecraft.dirt":29,"stat.useItem.minecraft.stone_slab2":67,"stat.mineBlock.mw.bauxiteore":3,"stat.pickup.minecraft.sand":203,"stat.craftItem.minecraft.furnace":2,"stat.craftItem.minecraft.stone_axe":6,"stat.drop.mw.pof308":1,"stat.craftItem.minecraft.stone_pickaxe":6,"stat.pickup.mw.leadore":3,"stat.craftItem.minecraft.cooked_beef":6,"stat.pickup.minecraft.cobblestone":404,"stat.mineBlock.minecraft.wooden_slab":1,"stat.flyOneCm":20211,"stat.pickup.minecraft.brown_mushroom":10,"stat.mineBlock.minecraft.sand":206,"stat.craftItem.ic2.ingot":5,"stat.craftItem.mw.copperingot":9,"stat.craftItem.minecraft.wooden_slab":102,"stat.pickup.minecraft.redstone":24,"stat.mineBlock.minecraft.iron_ore":23,"stat.timeSinceDeath":346593,"stat.useItem.minecraft.iron_pickaxe":325,"stat.craftItem.minecraft.wooden_pickaxe":1,"stat.useItem.minecraft.wooden_slab":84,"stat.pickup.minecraft.mutton":4,"stat.pickup.minecraft.mossy_cobblestone":1,"stat.mineBlock.mw.copperore":10,"stat.useItem.minecraft.oak_stairs":20,"stat.furnaceInteraction":53,"stat.killEntity.Wolf":1,"stat.pickup.minecraft.diamond_shovel":2,"stat.mineBlock.minecraft.coal_ore":107,"stat.craftItem.minecraft.stone_hoe":1,"stat.pickup.ic2.rubber_boots":1,"stat.pickup.minecraft.beef":6,"stat.pickup.minecraft.furnace":1,"stat.sprintOneCm":279712,"stat.craftItem.minecraft.gunpowder":13,"stat.useItem.minecraft.diamond_shovel":109,"stat.mineBlock.minecraft.stone_slab":17,"stat.useItem.minecraft.fence":35,"stat.craftItem.minecraft.stick":60,"stat.pickup.ic2.resource":10,"stat.useItem.minecraft.stone_slab":136,"stat.pickup.ic2.hazmat_helmet":1,"stat.craftItem.minecraft.stone":3,"stat.mineBlock.minecraft.diamond_ore":17,"stat.mineBlock.minecraft.crafting_table":4,"stat.pickup.ic2.misc_resource":5,"stat.mineBlock.minecraft.oak_stairs":4,"stat.mineBlock.minecraft.planks":61,"stat.drop":5,"stat.pickup.minecraft.egg":2,"stat.playOneMinute":346593,"stat.killEntity.Sheep":1,"stat.craftItem.minecraft.iron_pickaxe":2,"stat.pickup.ic2.hazmat_chestplate":1,"stat.mineBlock.minecraft.tallgrass":51,"stat.craftItem.minecraft.cooked_mutton":4,"stat.diveOneCm":5393,"stat.chestOpened":24,"stat.mineBlock.minecraft.mossy_cobblestone":1,"stat.useItem.minecraft.stone":7,"stat.pickup.minecraft.gravel":4,"stat.craftItem.minecraft.cooked_porkchop":7,"stat.craftItem.mw.aluminumingot":3,"stat.craftItem.minecraft.coal":1,"stat.jump":2596,"stat.pickup.minecraft.coal":106,"stat.fallOneCm":30510,"stat.pickup.minecraft.iron_ingot":3,"stat.useItem.minecraft.stone_axe":172,"stat.crouchOneCm":364,"stat.mineBlock.minecraft.chest":1,"stat.craftItem.minecraft.torch":12,"stat.craftItem.minecraft.iron_ingot":10,"stat.craftItem.minecraft.chest":6,"stat.pickup.minecraft.dirt":61,"stat.mineBlock.mw.leadore":3,"stat.craftingTableInteraction":62,"stat.pickup.minecraft.iron_ore":17,"stat.useItem.minecraft.glass":71,"stat.boatOneCm":28711,"stat.mineBlock.minecraft.lapis_ore":1,"stat.mineBlock.ic2.resource":10,"stat.damageTaken":460,"stat.pickup.minecraft.feather":1,"stat.pickup.minecraft.leather":3,"stat.mineBlock.minecraft.torch":1,"stat.useItem.minecraft.wooden_pickaxe":59,"stat.pickup.ic2.rubber_wood":127,"stat.pickup.minecraft.dye":1,"stat.pickup.minecraft.planks":374,"stat.pickup.minecraft.wheat_seeds":6,"stat.pickup.minecraft.oak_stairs":4,"stat.pickup.minecraft.lead":1,"stat.mineBlock.minecraft.gravel":5,"stat.useItem.ic2.rubber_wood":121,"stat.useItem.minecraft.stone_pickaxe":545,"stat.mineBlock.minecraft.glass":4,"stat.damageDealt":1039,"stat.craftItem.minecraft.glass":80,"stat.craftItem.minecraft.oak_stairs":28,"stat.killEntity.Cow":4,"stat.mineBlock.minecraft.dirt":62,"stat.killEntity.Pig":4,"stat.craftItem.minecraft.iron_sword":1,"stat.craftItem.minecraft.stone_slab":126,"stat.walkOneCm":1539631,"stat.useItem.minecraft.torch":10,"stat.pickup.mw.copperore":10,"stat.useItem.minecraft.chest":3,"stat.pickup.minecraft.stick":4,"stat.pickup.minecraft.crafting_table":4,"stat.useItem.minecraft.cobblestone":166,"stat.craftItem.minecraft.crafting_table":3,"stat.mineBlock.minecraft.double_plant":3,"stat.pickup.mw.pof308":1,"stat.craftItem.forestry.ingot_tin":18,"stat.pickup.minecraft.log":306,"stat.craftItem.forestry.ingot_copper":19,"stat.pickup.minecraft.stone":61,"stat.drop.minecraft.planks":2,"stat.pickup.minecraft.chicken":2,"stat.pickup.minecraft.sapling":164,"stat.pickup.minecraft.wooden_door":1,"stat.pickup.minecraft.air":0,"stat.pickup.minecraft.apple":14,"stat.craftItem.minecraft.planks":858,"stat.useItem.minecraft.iron_sword":25,"stat.killEntity.Chicken":2,"stat.mineBlock.forestry.resources":48,"stat.mobKills":12,"stat.mineBlock.minecraft.log":25,"stat.craftItem.minecraft.wooden_door":9,"stat.craftItem.minecraft.fence":39,"stat.craftItem.minecraft.cooked_chicken":2,"stat.useItem.minecraft.stone_hoe":1,"stat.pickup.forestry.ingot_tin":14,"stat.useItem.minecraft.wooden_door":7,"stat.useItem.minecraft.spruce_door":1,"stat.pickup.minecraft.diamond":9,"stat.mineBlock.minecraft.leaves":20,"stat.pickup.minecraft.torch":1,"stat.mineBlock.minecraft.redstone_ore":5,"stat.sneakTime":81,"stat.pickup.minecraft.wool":3,"stat.drop.minecraft.stone_axe":1,"stat.pickup.ic2.sapling":15,"stat.pickup.minecraft.stone_slab":68,"stat.mineBlock.minecraft.stone":413,"stat.pickup.minecraft.chest":2,"stat.craftItem.minecraft.spruce_door":3}